jnkn/__init__.py
jnkn/models.py
jnkn/analysis/__init__.py
jnkn/analysis/blast_radius.py
jnkn/analysis/diff_analyzer.py
jnkn/analysis/explain.py
jnkn/analysis/reviewers.py
jnkn/analysis/risk.py
jnkn/analysis/top_findings.py
jnkn/cli/__init__.py
jnkn/cli/formatting.py
jnkn/cli/main.py
jnkn/cli/renderers.py
jnkn/cli/utils.py
jnkn/cli/utils_telemetry.py
jnkn/cli/commands/__init__.py
jnkn/cli/commands/action.py
jnkn/cli/commands/blast_radius.py
jnkn/cli/commands/check.py
jnkn/cli/commands/diff.py
jnkn/cli/commands/explain.py
jnkn/cli/commands/feedback.py
jnkn/cli/commands/graph.py
jnkn/cli/commands/impact.py
jnkn/cli/commands/ingest.py
jnkn/cli/commands/initialize.py
jnkn/cli/commands/lint.py
jnkn/cli/commands/review.py
jnkn/cli/commands/scan.py
jnkn/cli/commands/stats.py
jnkn/cli/commands/suppress.py
jnkn/cli/commands/trace.py
jnkn/cli/commands/visualize.py
jnkn/cli/formatters/__init__.py
jnkn/cli/formatters/diff.py
jnkn/cli/formatters/findings.py
jnkn/cli/formatters/scan_summary.py
jnkn/core/__init__.py
jnkn/core/confidence.py
jnkn/core/demo.py
jnkn/core/exceptions.py
jnkn/core/graph.py
jnkn/core/interfaces.py
jnkn/core/mode.py
jnkn/core/result.py
jnkn/core/stitching.py
jnkn/core/telemetry.py
jnkn/core/types.py
jnkn/core/api/__init__.py
jnkn/core/api/envelope.py
jnkn/core/api/errors.py
jnkn/core/api/models.py
jnkn/core/packs/__init__.py
jnkn/core/packs/loader.py
jnkn/core/packs/definitions/django-aws.yaml
jnkn/core/packs/definitions/express-aws.yaml
jnkn/core/packs/definitions/fastapi-aws.yaml
jnkn/core/storage/__init__.py
jnkn/core/storage/base.py
jnkn/core/storage/memory.py
jnkn/core/storage/sqlite.py
jnkn/git/__init__.py
jnkn/git/diff_engine.py
jnkn/graph/__init__.py
jnkn/graph/lineage.py
jnkn/graph/store.py
jnkn/graph/visualize.py
jnkn/languages/__init__.py
jnkn/languages/parser.py
jnkn/languages/python/__init__.py
jnkn/languages/python/definitions.scm
jnkn/languages/python/imports.scm
jnkn/languages/terraform/__init__.py
jnkn/languages/terraform/resources.scm
jnkn-0.0.0rc7.dist-info/METADATA
jnkn-0.0.0rc7.dist-info/WHEEL
jnkn-0.0.0rc7.dist-info/entry_points.txt
jnkn-0.0.0rc7.dist-info/RECORD
