Metadata-Version: 2.4
Name: jnkn
Version: 0.0.0rc7
Summary: The Pre-Flight Impact Analysis Engine for Engineering Teams.
Project-URL: Documentation, https://bordumb.github.io/jnkn/
Project-URL: Repository, https://github.com/bordumb/jnkn
Project-URL: Issues, https://github.com/bordumb/jnkn/issuess
Author-email: Bordumb <bordumbb@gmail.com>
License: MIT
Classifier: Development Status :: 4 - Beta
Classifier: Intended Audience :: Developers
Classifier: License :: OSI Approved :: MIT License
Classifier: Operating System :: OS Independent
Classifier: Programming Language :: Python :: 3.12
Classifier: Topic :: Software Development :: Build Tools
Requires-Python: >=3.12
Requires-Dist: click>=8.1.7
Requires-Dist: openlineage-python>=1.40.1
Requires-Dist: pydantic>=2.5.0
Requires-Dist: pyyaml>=6.0.0
Requires-Dist: rich>=13.7.0
Requires-Dist: rustworkx>=0.17.1
Provides-Extra: dev
Requires-Dist: pytest-cov>=4.1.0; extra == 'dev'
Requires-Dist: pytest>=7.4.0; extra == 'dev'
Requires-Dist: ruff>=0.1.0; extra == 'dev'
Provides-Extra: docs
Requires-Dist: mike; extra == 'docs'
Requires-Dist: mkdocs-gen-files; extra == 'docs'
Requires-Dist: mkdocs-literate-nav; extra == 'docs'
Requires-Dist: mkdocs-material; extra == 'docs'
Requires-Dist: mkdocs-redirects; extra == 'docs'
Requires-Dist: mkdocs-section-index; extra == 'docs'
Requires-Dist: mkdocstrings-python; extra == 'docs'
Provides-Extra: full
Requires-Dist: httpx>=0.27.0; extra == 'full'
Requires-Dist: sqlglot>=20.0.0; extra == 'full'
Requires-Dist: tree-sitter-languages>=1.10.2; extra == 'full'
Requires-Dist: tree-sitter==0.21.3; extra == 'full'
Requires-Dist: xxhash>=3.4.1; extra == 'full'
